thehivebackup/__init__.py
thehivebackup/backup.py
thehivebackup/empty.py
thehivebackup/main.py
thehivebackup/migrate3to4.py
thehivebackup/restore.py
thehivebackup-0.1.5.dist-info/LICENSE
thehivebackup-0.1.5.dist-info/METADATA
thehivebackup-0.1.5.dist-info/WHEEL
thehivebackup-0.1.5.dist-info/entry_points.txt
thehivebackup-0.1.5.dist-info/top_level.txt
thehivebackup-0.1.5.dist-info/RECORD
