Metadata-Version: 2.1
Name: thehivebackup
Version: 0.1.5
Summary: Backup and restore TheHive remotely
Home-page: https://github.com/IFX-CDC/thehivebackup
Author: Anton Piiroja & Jonas Plum
License: UNKNOWN
Platform: UNKNOWN
Classifier: Programming Language :: Python :: 3
Classifier: License :: OSI Approved :: MIT License
Classifier: Operating System :: OS Independent
License-File: LICENSE
Requires-Dist: requests (==2.25.1)
Requires-Dist: thehive4py (==1.8.1)
